mgplot/__init__.py
mgplot/axis_utils.py
mgplot/bar_plot.py
mgplot/colors.py
mgplot/fill_between_plot.py
mgplot/finalise_plot.py
mgplot/finalisers.py
mgplot/growth_plot.py
mgplot/keyword_checking.py
mgplot/line_plot.py
mgplot/lint-all.sh
mgplot/multi_plot.py
mgplot/postcovid_plot.py
mgplot/py.typed
mgplot/revision_plot.py
mgplot/run_plot.py
mgplot/seastrend_plot.py
mgplot/settings.py
mgplot/summary_plot.py
mgplot/utilities.py
mgplot-0.2.18.dist-info/METADATA
mgplot-0.2.18.dist-info/WHEEL
mgplot-0.2.18.dist-info/licenses/LICENSE
mgplot-0.2.18.dist-info/RECORD
