Metadata-Version: 2.4
Name: mgplot
Version: 0.2.18
Summary: mgplot is a time-series/PeriodIndex frontend for matplotlib
Project-URL: Repository, https://github.com/bpalmer4/mgplot
Project-URL: Homepage, https://github.com/bpalmer4/mgplot
License-File: LICENSE
Requires-Python: >=3.12
Requires-Dist: matplotlib
Requires-Dist: numpy
Requires-Dist: pandas
Requires-Dist: pathlib
Requires-Dist: tabulate
Requires-Dist: typing
